{
  "date": "2026-04-02",
  "window_days": 251,
  "tickers": [
    "CMIG3.SA",
    "MDNE3.SA",
    "PLPL3.SA",
    "SAPR11.SA",
    "TEND3.SA",
    "VULC3.SA",
    "AURA33.SA",
    "PETR3.SA",
    "VALE3.SA",
    "AXIA6.SA",
    "DASA3.SA",
    "ENEV3.SA",
    "PNVL3.SA"
  ],
  "groups": {
    "AURA33.SA": "both",
    "AXIA6.SA": "model",
    "CMIG3.SA": "holdings",
    "DASA3.SA": "model",
    "ENEV3.SA": "model",
    "MDNE3.SA": "holdings",
    "PETR3.SA": "both",
    "PLPL3.SA": "holdings",
    "PNVL3.SA": "model",
    "SAPR11.SA": "holdings",
    "TEND3.SA": "holdings",
    "VALE3.SA": "both",
    "VULC3.SA": "holdings"
  },
  "matrix": [
    [
      1.0,
      0.2704,
      0.1687,
      0.3798,
      0.1933,
      0.2463,
      0.1546,
      0.1781,
      0.1542,
      0.2827,
      0.1273,
      0.2127,
      0.2662
    ],
    [
      0.2704,
      1.0,
      0.4845,
      0.3408,
      0.4882,
      0.3458,
      0.2297,
      0.0722,
      0.1716,
      0.3648,
      0.2946,
      0.3614,
      0.3193
    ],
    [
      0.1687,
      0.4845,
      1.0,
      0.2049,
      0.6059,
      0.3914,
      0.2223,
      0.0872,
      0.178,
      0.3801,
      0.1882,
      0.253,
      0.2812
    ],
    [
      0.3798,
      0.3408,
      0.2049,
      1.0,
      0.2114,
      0.2757,
      0.1959,
      0.1027,
      0.1564,
      0.3624,
      0.2176,
      0.2927,
      0.3475
    ],
    [
      0.1933,
      0.4882,
      0.6059,
      0.2114,
      1.0,
      0.3065,
      0.1769,
      0.2209,
      0.1037,
      0.4091,
      0.2202,
      0.2756,
      0.3473
    ],
    [
      0.2463,
      0.3458,
      0.3914,
      0.2757,
      0.3065,
      1.0,
      0.0609,
      0.1106,
      0.1891,
      0.3717,
      0.2307,
      0.2722,
      0.3427
    ],
    [
      0.1546,
      0.2297,
      0.2223,
      0.1959,
      0.1769,
      0.0609,
      1.0,
      0.0161,
      0.3224,
      0.2161,
      0.0666,
      0.0656,
      0.1258
    ],
    [
      0.1781,
      0.0722,
      0.0872,
      0.1027,
      0.2209,
      0.1106,
      0.0161,
      1.0,
      0.1328,
      0.0676,
      0.0835,
      0.0958,
      0.088
    ],
    [
      0.1542,
      0.1716,
      0.178,
      0.1564,
      0.1037,
      0.1891,
      0.3224,
      0.1328,
      1.0,
      0.2735,
      0.1967,
      0.1089,
      0.2878
    ],
    [
      0.2827,
      0.3648,
      0.3801,
      0.3624,
      0.4091,
      0.3717,
      0.2161,
      0.0676,
      0.2735,
      1.0,
      0.2542,
      0.4206,
      0.478
    ],
    [
      0.1273,
      0.2946,
      0.1882,
      0.2176,
      0.2202,
      0.2307,
      0.0666,
      0.0835,
      0.1967,
      0.2542,
      1.0,
      0.1988,
      0.2494
    ],
    [
      0.2127,
      0.3614,
      0.253,
      0.2927,
      0.2756,
      0.2722,
      0.0656,
      0.0958,
      0.1089,
      0.4206,
      0.1988,
      1.0,
      0.3137
    ],
    [
      0.2662,
      0.3193,
      0.2812,
      0.3475,
      0.3473,
      0.3427,
      0.1258,
      0.088,
      0.2878,
      0.478,
      0.2494,
      0.3137,
      1.0
    ]
  ]
}